pybt/__init__.py
pybt/core/__init__.py
pybt/core/core.py
pybt/core/util.py
pybt/tests/__init__.py
pybt/tests/simple_nonclass_test.py
pybt/tests/simple_unit_test.py
python_property_based_testing-0.9.2.dist-info/LICENSE
python_property_based_testing-0.9.2.dist-info/METADATA
python_property_based_testing-0.9.2.dist-info/WHEEL
python_property_based_testing-0.9.2.dist-info/RECORD
