Metadata-Version: 2.1
Name: python-property-based-testing
Version: 0.9.2
Summary: Property Based Testing in Python
Author: vrindisbacher
Author-email: vrindisbacher77@gmail.com
Requires-Python: >=3.10,<=3.12
Classifier: Programming Language :: Python :: 3
Classifier: Programming Language :: Python :: 3.10
Classifier: Programming Language :: Python :: 3.11
